setup.py
t_decorators/__init__.py
t_decorators.egg-info/PKG-INFO
t_decorators.egg-info/SOURCES.txt
t_decorators.egg-info/dependency_links.txt
t_decorators.egg-info/top_level.txt
t_decorators.egg-info/zip-safe