Metadata-Version: 1.0
Name: t-decorators
Version: 0.1
Summary: T decorator library
Home-page: https://gitlab.com/ddmello/lib/python/t_decorators.git
Author: Darrin D'Mello
Author-email: darrin.dmello@gmail.com
License: MIT
Platform: UNKNOWN
